stow/__init__.py
stow/callbacks.py
stow/cli.py
stow/exceptions.py
stow/localiser.py
stow/storage_classes.py
stow/types.py
stow/utils.py
stow/worker_config.py
stow/artefacts/__init__.py
stow/artefacts/artefacts.py
stow/artefacts/interfaces.py
stow/artefacts/types.py
stow/manager/__init__.py
stow/manager/abstract_methods.py
stow/manager/base_managers.py
stow/manager/configs.py
stow/manager/manager.py
stow/managers/__init__.py
stow/managers/amazon.py
stow/managers/filesystem.py
stow/managers/google.py
stow/managers/kubernetes.py
stow/managers/ssh.py
stow-1.4.1.dist-info/LICENSE
stow-1.4.1.dist-info/METADATA
stow-1.4.1.dist-info/WHEEL
stow-1.4.1.dist-info/entry_points.txt
stow-1.4.1.dist-info/top_level.txt
stow-1.4.1.dist-info/RECORD
