Metadata-Version: 2.1
Name: stow
Version: 1.4.1
Summary: stow artefacts anywhere, with ease
Author: Kieran Bacon
Author-email: kieran.bacon@outlook.com
Project-URL: Homepage, https://github.com/Kieran-Bacon/stow
Project-URL: Documentation, https://stow.readthedocs.io/en/latest/
Project-URL: Bug Tracker, https://github.com/Kieran-Bacon/stow/issues
Keywords: aws s3 boto3 ssh os
Classifier: Programming Language :: Python :: 3
Classifier: License :: OSI Approved :: Apache Software License
Classifier: Operating System :: OS Independent
License-File: LICENSE
Requires-Dist: tqdm
Requires-Dist: typing-extensions
Provides-Extra: all
Requires-Dist: boto3 ; extra == 'all'
Requires-Dist: click ; extra == 'all'
Requires-Dist: click-option-group ; extra == 'all'
Requires-Dist: google-api-python-client ; extra == 'all'
Requires-Dist: google-auth-httplib2 ; extra == 'all'
Requires-Dist: google-auth-oauthlib ; extra == 'all'
Provides-Extra: cli
Requires-Dist: click ; extra == 'cli'
Requires-Dist: click-option-group ; extra == 'cli'
Provides-Extra: drive
Requires-Dist: google-api-python-client ; extra == 'drive'
Requires-Dist: google-auth-httplib2 ; extra == 'drive'
Requires-Dist: google-auth-oauthlib ; extra == 'drive'
Provides-Extra: s3
Requires-Dist: boto3 ; extra == 's3'
Provides-Extra: test
Requires-Dist: pyini ; extra == 'test'
Requires-Dist: pytest ; extra == 'test'
Requires-Dist: pytest-cov ; extra == 'test'
Requires-Dist: moto[s3] >=4.1.5.dev40 ; extra == 'test'
Requires-Dist: mkdocs ; extra == 'test'
Requires-Dist: mkdocstrings[python] ==0.22.0 ; extra == 'test'
Requires-Dist: click ; extra == 'test'
Requires-Dist: click-option-group ; extra == 'test'
Requires-Dist: boto3-stubs[s3] ; extra == 'test'
Requires-Dist: crc32c ; extra == 'test'
